{"data":{"id":"polygon_pos_0x746cf1baaa81e6f2dee39bd4e3cb5e9f0edf98a8","type":"pool","attributes":{"base_token_price_usd":"0.0673796705460638","base_token_price_native_currency":"0.000037531115493047837851590375531152585463073","quote_token_price_usd":"0.182346044452445","quote_token_price_native_currency":"0.00010157874930503","base_token_price_quote_token":"0.3694780232","quote_token_price_base_token":"2.7065209219","address":"0x746cf1baaa81e6f2dee39bd4e3cb5e9f0edf98a8","name":"CTZN / WPOL 0.01%","pool_created_at":"2025-03-24T16:59:00Z","fdv_usd":"467215.592234354","market_cap_usd":null,"price_change_percentage":{"m5":"0","m15":"0","m30":"0","h1":"0","h6":"0","h24":"0"},"transactions":{"m5":{"buys":0,"sells":0,"buyers":0,"sellers":0},"m15":{"buys":0,"sells":0,"buyers":0,"sellers":0},"m30":{"buys":0,"sells":0,"buyers":0,"sellers":0},"h1":{"buys":0,"sells":0,"buyers":0,"sellers":0},"h6":{"buys":0,"sells":0,"buyers":0,"sellers":0},"h24":{"buys":1,"sells":0,"buyers":1,"sellers":0}},"volume_usd":{"m5":"0.0","m15":"0.0","m30":"0.0","h1":"0.0","h6":"0.0","h24":"0.2935704002"},"reserve_in_usd":"76374.7276","locked_liquidity_percentage":null},"relationships":{"base_token":{"data":{"id":"polygon_pos_0x0d9b0790e97e3426c161580df4ee853e4a7c4607","type":"token"}},"quote_token":{"data":{"id":"polygon_pos_0x0d500b1d8e8ef31e21c99d1db9a6444d3adf1270","type":"token"}},"dex":{"data":{"id":"quickswap_v3","type":"dex"}}}}}